khed/__init__.py
khed/anime.py
khed/args.py
khed/downloader.py
khed/interface.py
khed/api/__init__.py
khed/api/sites/__init__.py
khed/api/sites/chianime.py
khed-0.0.2.dist-info/LICENSE
khed-0.0.2.dist-info/METADATA
khed-0.0.2.dist-info/WHEEL
khed-0.0.2.dist-info/entry_points.txt
khed-0.0.2.dist-info/top_level.txt
khed-0.0.2.dist-info/RECORD
