Metadata-Version: 2.1
Name: khed
Version: 0.0.2
Summary: Free anime downloader, supporting resumable downloads and episodes playlist all at once.
Home-page: UNKNOWN
Author: Bhanu Kashyap
Author-email: kash.bhanu7@gmail.com
License: MIT
Platform: UNKNOWN
Classifier: License :: OSI Approved :: MIT License
Classifier: Operating System :: POSIX :: Linux
Classifier: Environment :: Console
Classifier: Programming Language :: Python :: 3.6
Classifier: Programming Language :: Python :: 3.5
Classifier: Programming Language :: Python :: 3.4
Classifier: Topic :: Multimedia :: Video
Requires-Dist: beautifulsoup4
Requires-Dist: bs4
Requires-Dist: lxml
Requires-Dist: requests
Requires-Dist: selenium
Requires-Dist: tqdm
